{
  "id": "f5d16838-a733-424d-bb02-5a58218b7ac4",
  "checksum": "3f7c997772e9ac7eef0c4c6ff8dbac75",
  "words": {
    "applies": [
      "h2"
    ],
    "to": [
      "h2",
      "h2",
      "p",
      "p",
      "ol",
      "ol",
      "ol",
      "li",
      "li",
      "li",
      "strong"
    ],
    "web": [
      "ul",
      "li",
      "p",
      "ol",
      "ol",
      "ol",
      "ol",
      "li",
      "li",
      "li",
      "li",
      "strong"
    ],
    "applications": [
      "ul",
      "li"
    ],
    "what": [
      "h2"
    ],
    "do": [
      "h2"
    ],
    "disable": [
      "p",
      "p",
      "p",
      "ol",
      "li",
      "strong",
      "title"
    ],
    "directory": [
      "p",
      "p",
      "p",
      "p",
      "p",
      "ol",
      "ol",
      "ol",
      "ol",
      "li",
      "strong",
      "li",
      "li",
      "li",
      "strong",
      "title"
    ],
    "browsing": [
      "p",
      "p",
      "p",
      "p",
      "ol",
      "ol",
      "ol",
      "ol",
      "li",
      "strong",
      "li",
      "li",
      "li",
      "strong",
      "title"
    ],
    "for": [
      "p",
      "ol",
      "ol",
      "ol",
      "ol",
      "li",
      "li",
      "li",
      "li"
    ],
    "your": [
      "p",
      "p",
      "ol",
      "ol",
      "ol",
      "li",
      "li",
      "li"
    ],
    "application's": [
      "p",
      "p",
      "ol",
      "ol",
      "li",
      "li"
    ],
    "directories": [
      "p",
      "ol",
      "li"
    ],
    "why": [
      "h2"
    ],
    "allows": [
      "p"
    ],
    "an": [
      "p",
      "ol",
      "li"
    ],
    "attacker": [
      "p"
    ],
    "browse": [
      "p"
    ],
    "structure": [
      "p"
    ],
    "in": [
      "p"
    ],
    "search": [
      "p"
    ],
    "of": [
      "p"
    ],
    "unprotected": [
      "p"
    ],
    "files": [
      "p"
    ],
    "and": [
      "p"
    ],
    "components": [
      "p"
    ],
    "when": [
      "h2"
    ],
    "at": [
      "p"
    ],
    "all": [
      "p"
    ],
    "times": [
      "p"
    ],
    "how": [
      "h2"
    ],
    "use": [
      "p"
    ],
    "the": [
      "p",
      "ol",
      "ol",
      "li",
      "li",
      "strong"
    ],
    "following": [
      "p"
    ],
    "steps": [
      "p"
    ],
    "successfully": [
      "p"
    ],
    "identify": [
      "ol",
      "ol",
      "li",
      "li",
      "strong"
    ],
    "if": [
      "ol",
      "li",
      "strong"
    ],
    "is": [
      "ol",
      "li",
      "strong"
    ],
    "enabled": [
      "ol",
      "li",
      "strong"
    ],
    "navigate": [
      "ol",
      "li"
    ],
    "with": [
      "ol",
      "li"
    ],
    "a": [
      "ol",
      "li"
    ],
    "browser": [
      "ol",
      "li"
    ],
    "whether": [
      "ol",
      "li"
    ],
    "server": [
      "ol",
      "ol",
      "li",
      "li",
      "strong"
    ],
    "correctly": [
      "ol",
      "li"
    ],
    "returns": [
      "ol",
      "li"
    ],
    "http": [
      "ol",
      "li"
    ],
    "error": [
      "ol",
      "li"
    ],
    "message": [
      "ol",
      "li"
    ],
    "configure": [
      "ol",
      "li",
      "strong"
    ],
    "exact": [
      "ol",
      "li"
    ],
    "procedures": [
      "ol",
      "li"
    ],
    "disabling": [
      "ol",
      "ol",
      "li",
      "li"
    ],
    "are": [
      "ol",
      "li"
    ],
    "different": [
      "ol",
      "ol",
      "li",
      "li"
    ],
    "servers": [
      "ol",
      "li"
    ],
    "please": [
      "ol",
      "li"
    ],
    "refer": [
      "ol",
      "li"
    ],
    "server's": [
      "ol",
      "li"
    ],
    "documentation": [
      "ol",
      "li"
    ],
    "detailed": [
      "ol",
      "li"
    ],
    "instructions": [
      "ol",
      "li"
    ]
  },
  "tags": {},
  "links": []
}