{
  "id": "6e31f64e-8c69-44e7-9627-c3ae6a354c50",
  "checksum": "0ea1e5c827431c9cab678c2a51148de7",
  "words": {
    "applies": [
      "h2"
    ],
    "to": [
      "h2",
      "h2",
      "p",
      "ol",
      "ol",
      "ol",
      "ol",
      "ol",
      "ol",
      "li",
      "li",
      "li",
      "li",
      "li",
      "li",
      "strong"
    ],
    "web": [
      "ul",
      "li",
      "ol",
      "ol",
      "ol",
      "li",
      "li",
      "li",
      "strong",
      "ul",
      "li"
    ],
    "applications": [
      "ul",
      "li"
    ],
    "what": [
      "h2"
    ],
    "do": [
      "h2"
    ],
    "use": [
      "p",
      "p",
      "ol",
      "ol",
      "li",
      "li",
      "strong",
      "title"
    ],
    "valid": [
      "p",
      "p",
      "p",
      "ol",
      "ol",
      "ol",
      "li",
      "li",
      "strong",
      "li",
      "strong",
      "title"
    ],
    "tls": [
      "p",
      "p",
      "p",
      "ol",
      "ol",
      "ol",
      "ol",
      "ol",
      "ol",
      "ol",
      "ol",
      "ol",
      "li",
      "li",
      "li",
      "strong",
      "li",
      "li",
      "li",
      "strong",
      "li",
      "li",
      "li",
      "strong",
      "ul",
      "li",
      "title"
    ],
    "certificates": [
      "p",
      "p",
      "ol",
      "ol",
      "ol",
      "li",
      "li",
      "li",
      "ul",
      "li",
      "title"
    ],
    "why": [
      "h2"
    ],
    "using": [
      "p"
    ],
    "helps": [
      "p"
    ],
    "prevent": [
      "p"
    ],
    "phishing": [
      "p"
    ],
    "attacks": [
      "p"
    ],
    "by": [
      "p",
      "ol",
      "li"
    ],
    "assuring": [
      "p"
    ],
    "visitors": [
      "p"
    ],
    "that": [
      "p"
    ],
    "your": [
      "p",
      "ol",
      "ol",
      "ol",
      "li",
      "li",
      "li"
    ],
    "site": [
      "p"
    ],
    "is": [
      "p",
      "ol",
      "li"
    ],
    "secure": [
      "p"
    ],
    "and": [
      "p"
    ],
    "trusted": [
      "p"
    ],
    "how": [
      "h2",
      "ol",
      "ol",
      "li",
      "li"
    ],
    "a": [
      "p",
      "ol",
      "ol",
      "ol",
      "li",
      "li",
      "li",
      "strong"
    ],
    "certificate": [
      "p",
      "ol",
      "ol",
      "ol",
      "ol",
      "ol",
      "li",
      "li",
      "li",
      "li",
      "strong",
      "li",
      "strong"
    ],
    "purchase": [
      "ol",
      "ol",
      "li",
      "li",
      "strong"
    ],
    "you": [
      "ol",
      "li"
    ],
    "may": [
      "ol",
      "li"
    ],
    "key": [
      "ol",
      "li"
    ],
    "from": [
      "ol",
      "li"
    ],
    "verisign": [
      "ol",
      "li"
    ],
    "thawte": [
      "ol",
      "li"
    ],
    "or": [
      "ol",
      "ol",
      "ol",
      "li",
      "li",
      "li"
    ],
    "hosting": [
      "ol",
      "li"
    ],
    "provider": [
      "ol",
      "li"
    ],
    "follow": [
      "ol",
      "li"
    ],
    "the": [
      "ol",
      "ol",
      "ol",
      "ol",
      "ol",
      "ol",
      "ol",
      "ol",
      "ol",
      "li",
      "li",
      "li",
      "li",
      "li",
      "li",
      "li",
      "strong",
      "li",
      "li",
      "strong"
    ],
    "vendor's": [
      "ol",
      "li"
    ],
    "instructions": [
      "ol",
      "ol",
      "ol",
      "ol",
      "ol",
      "li",
      "li",
      "li",
      "li",
      "li"
    ],
    "for": [
      "ol",
      "ol",
      "ol",
      "ol",
      "ol",
      "ol",
      "ol",
      "li",
      "li",
      "li",
      "li",
      "li",
      "li",
      "li",
      "ul",
      "li"
    ],
    "purchasing": [
      "ol",
      "li"
    ],
    "usually": [
      "ol",
      "li"
    ],
    "cer": [
      "ol",
      "li"
    ],
    "file": [
      "ol",
      "li"
    ],
    "make": [
      "ol",
      "li"
    ],
    "sure": [
      "ol",
      "li"
    ],
    "matches": [
      "ol",
      "li"
    ],
    "all": [
      "ol",
      "li"
    ],
    "domains": [
      "ol",
      "li"
    ],
    "used": [
      "ol",
      "li"
    ],
    "application": [
      "ol",
      "ol",
      "ol",
      "ol",
      "ol",
      "ol",
      "li",
      "li",
      "li",
      "li",
      "li",
      "li",
      "strong"
    ],
    "import": [
      "ol",
      "li",
      "strong"
    ],
    "exact": [
      "ol",
      "ol",
      "li",
      "li"
    ],
    "importing": [
      "ol",
      "li",
      "ul",
      "li"
    ],
    "are": [
      "ol",
      "ol",
      "li",
      "li"
    ],
    "different": [
      "ol",
      "ol",
      "ol",
      "ol",
      "li",
      "li",
      "li",
      "li"
    ],
    "servers": [
      "ol",
      "ol",
      "li",
      "li",
      "ul",
      "li"
    ],
    "please": [
      "ol",
      "ol",
      "li",
      "li",
      "ul",
      "li"
    ],
    "refer": [
      "ol",
      "ol",
      "li",
      "li"
    ],
    "server's": [
      "ol",
      "ol",
      "li",
      "li"
    ],
    "documentation": [
      "ol",
      "ol",
      "li",
      "li"
    ],
    "technical": [
      "ol",
      "ol",
      "li",
      "li"
    ],
    "support": [
      "ol",
      "ol",
      "li",
      "li"
    ],
    "detailed": [
      "ol",
      "ol",
      "li",
      "li"
    ],
    "on": [
      "ol",
      "ol",
      "li",
      "li"
    ],
    "install": [
      "ol",
      "ol",
      "li",
      "li"
    ],
    "configure": [
      "ol",
      "li",
      "strong"
    ],
    "server": [
      "ol",
      "li",
      "strong"
    ],
    "configuring": [
      "ol",
      "li"
    ],
    "platforms": [
      "ol",
      "li"
    ],
    "additional": [
      "h2"
    ],
    "resources": [
      "h2"
    ],
    "more": [
      "ul",
      "li"
    ],
    "information": [
      "ul",
      "li"
    ],
    "about": [
      "ul",
      "li"
    ],
    "into": [
      "ul",
      "li"
    ],
    "common": [
      "ul",
      "li"
    ],
    "see": [
      "ul",
      "li"
    ],
    "http//www.directnic.com/help/guides/index.php?guide_id=7": [
      "ul",
      "li",
      "a"
    ]
  },
  "tags": {},
  "links": [
    {
      "href": "http://www.directnic.com/help/guides/index.php?guide_id=7",
      "text": "http://www.directnic.com/help/guides/index.php?guide_id=7"
    }
  ]
}