{
  "id": "6ac43864-2644-4f33-bfb2-1366c5c3cb58",
  "checksum": "332b79c1e3876e461a0111a4bf86fe4b",
  "words": {
    "applies": [
      "h1"
    ],
    "to": [
      "h1",
      "h1",
      "p",
      "p",
      "p",
      "ol",
      "ol",
      "li",
      "li",
      "p",
      "p"
    ],
    "scala": [
      "p"
    ],
    "and": [
      "p",
      "ol",
      "li",
      "p"
    ],
    "play": [
      "p"
    ],
    "framework": [
      "p"
    ],
    "21.0+": [
      "p"
    ],
    "what": [
      "h1"
    ],
    "do": [
      "h1"
    ],
    "make": [
      "p",
      "p",
      "p",
      "p",
      "title"
    ],
    "inactive": [
      "p",
      "p",
      "ol",
      "li",
      "p",
      "strong",
      "title"
    ],
    "sessions": [
      "p",
      "p",
      "p",
      "title"
    ],
    "time": [
      "p",
      "p",
      "ol",
      "li",
      "p",
      "strong",
      "title"
    ],
    "out": [
      "p",
      "p",
      "ol",
      "li",
      "p",
      "strong",
      "title"
    ],
    "why": [
      "h1"
    ],
    "expire": [
      "p"
    ],
    "after": [
      "p"
    ],
    "a": [
      "p",
      "p",
      "ol",
      "ol",
      "ol",
      "ol",
      "li",
      "li",
      "li",
      "li",
      "p",
      "p",
      "p",
      "p"
    ],
    "period": [
      "p",
      "strong"
    ],
    "of": [
      "p"
    ],
    "inactivity": [
      "p",
      "ol",
      "li",
      "p"
    ],
    "it": [
      "p",
      "ol",
      "ol",
      "li",
      "li",
      "p",
      "p"
    ],
    "harder": [
      "p"
    ],
    "for": [
      "p",
      "ol",
      "ol",
      "ol",
      "li",
      "li",
      "li",
      "p",
      "p",
      "p",
      "ul",
      "li"
    ],
    "an": [
      "p"
    ],
    "attacker": [
      "p"
    ],
    "hijack": [
      "p"
    ],
    "session": [
      "p",
      "ol",
      "ol",
      "ol",
      "ol",
      "ol",
      "li",
      "li",
      "li",
      "li",
      "li",
      "p",
      "p",
      "strong",
      "p",
      "p",
      "p"
    ],
    "how": [
      "h1",
      "ol",
      "li",
      "p"
    ],
    "identify": [
      "ol",
      "li",
      "p",
      "strong"
    ],
    "login": [
      "ol",
      "li",
      "p",
      "strong"
    ],
    "functionality find": [
      "ol",
      "li",
      "p"
    ],
    "code": [
      "ol",
      "ol",
      "li",
      "p",
      "li",
      "p",
      "strong"
    ],
    "that": [
      "ol",
      "ol",
      "li",
      "p",
      "li",
      "p",
      "strong"
    ],
    "handles": [
      "ol",
      "li",
      "p"
    ],
    "user": [
      "ol",
      "ol",
      "ol",
      "li",
      "p",
      "li",
      "li",
      "p",
      "p"
    ],
    "logins": [
      "ol",
      "li",
      "p"
    ],
    "add": [
      "ol",
      "ol",
      "li",
      "li",
      "p",
      "strong",
      "p"
    ],
    "sets": [
      "ol",
      "li",
      "p",
      "strong"
    ],
    "the": [
      "ol",
      "ol",
      "ol",
      "ol",
      "ol",
      "ol",
      "ol",
      "li",
      "li",
      "li",
      "li",
      "li",
      "li",
      "li",
      "p",
      "p",
      "p",
      "p",
      "strong",
      "p",
      "p",
      "p"
    ],
    "period there": [
      "ol",
      "li",
      "p"
    ],
    "is": [
      "ol",
      "li",
      "p"
    ],
    "no": [
      "ol",
      "li",
      "p"
    ],
    "technical": [
      "ol",
      "li",
      "p"
    ],
    "timeout": [
      "ol",
      "ol",
      "ol",
      "li",
      "li",
      "li",
      "p",
      "p",
      "p"
    ],
    "expires": [
      "ol",
      "li",
      "p"
    ],
    "when": [
      "ol",
      "li",
      "p"
    ],
    "closes": [
      "ol",
      "li",
      "p"
    ],
    "web": [
      "ol",
      "li",
      "p"
    ],
    "browser": [
      "ol",
      "li",
      "p"
    ],
    "if": [
      "ol",
      "li",
      "p"
    ],
    "you": [
      "ol",
      "li",
      "p"
    ],
    "need": [
      "ol",
      "li",
      "p"
    ],
    "functional": [
      "ol",
      "li",
      "p"
    ],
    "specific": [
      "ol",
      "li",
      "p"
    ],
    "application": [
      "ol",
      "ol",
      "ol",
      "li",
      "li",
      "li",
      "p",
      "p",
      "p"
    ],
    "store": [
      "ol",
      "li",
      "p"
    ],
    "timestamp": [
      "ol",
      "li",
      "p"
    ],
    "into": [
      "ol",
      "li",
      "p"
    ],
    "use": [
      "ol",
      "li",
      "p"
    ],
    "in": [
      "ol",
      "li",
      "p"
    ],
    "way": [
      "ol",
      "li",
      "p"
    ],
    "your": [
      "ol",
      "li",
      "p"
    ],
    "needs": [
      "ol",
      "li",
      "p"
    ],
    "e.g.": [
      "ol",
      "li",
      "p"
    ],
    "maximum": [
      "ol",
      "ol",
      "li",
      "li",
      "p",
      "p"
    ],
    "duration": [
      "ol",
      "ol",
      "li",
      "li",
      "p",
      "p"
    ],
    "etc). this link": [
      "ol",
      "li",
      "p"
    ],
    "explains": [
      "ol",
      "li",
      "p"
    ],
    "functionality": [
      "ol",
      "strong",
      "li",
      "p"
    ],
    "this": [
      "a"
    ],
    "additional": [
      "h1"
    ],
    "resources": [
      "h1"
    ],
    "more": [
      "ul",
      "li"
    ],
    "information": [
      "ul",
      "li"
    ],
    "about": [
      "ul",
      "li"
    ],
    "the method": [
      "ul",
      "li"
    ],
    "please": [
      "ul",
      "li"
    ],
    "see https://github.com/jroper/play": [
      "ul",
      "li"
    ],
    "security": [
      "ul",
      "li",
      "a"
    ],
    "utils/blob/master/src/main/scala/play/security/utils/sessiontimeoutaction.scala": [
      "ul",
      "li",
      "a"
    ],
    "https//github.com/jroper/play": [
      "a"
    ]
  },
  "tags": {},
  "links": [
    {
      "href": "https://github.com/jroper/play-security-utils/",
      "text": "This"
    },
    {
      "href": "http://download.oracle.com/javaee/6/api/javax/servlet/http/HttpSession.html#setMaxInactiveInterval%28int%29",
      "text": ":"
    },
    {
      "href": "https://github.com/jroper/play-security-utils/blob/master/src/main/scala/play/security/utils/SessionTimeoutAction.scala",
      "text": "https://github.com/jroper/play-security-utils/blob/master/src/main/scala/play/security/utils/SessionTimeoutAction.scala"
    }
  ]
}