{
  "id": "f14408bf-7874-4514-a440-48dca88c6afb",
  "checksum": "d06dc73f58b3fac69be2ba5f39abd365",
  "words": {
    "what": [
      "h2"
    ],
    "to": [
      "h2",
      "p",
      "p",
      "p",
      "p",
      "p",
      "p",
      "p",
      "ol",
      "ol",
      "ol",
      "li",
      "p",
      "li",
      "li",
      "p",
      "p",
      "strong",
      "title"
    ],
    "do": [
      "h2"
    ],
    "use": [
      "p",
      "ol",
      "ol",
      "ol",
      "li",
      "p",
      "strong",
      "li",
      "li",
      "p",
      "p",
      "strong",
      "title"
    ],
    "regular": [
      "p",
      "p",
      "p",
      "ol",
      "ol",
      "ol",
      "ol",
      "ol",
      "ol",
      "ol",
      "ol",
      "li",
      "li",
      "li",
      "p",
      "p",
      "p",
      "strong",
      "li",
      "p",
      "li",
      "li",
      "p",
      "p",
      "strong",
      "li",
      "li",
      "p",
      "p",
      "strong",
      "ul",
      "li",
      "title"
    ],
    "expressions": [
      "p",
      "p",
      "p",
      "ol",
      "ol",
      "ol",
      "ol",
      "ol",
      "li",
      "p",
      "li",
      "li",
      "p",
      "p",
      "strong",
      "li",
      "li",
      "p",
      "p",
      "strong",
      "ul",
      "li",
      "title"
    ],
    "validate": [
      "p",
      "ol",
      "li",
      "p",
      "strong",
      "title"
    ],
    "input": [
      "p",
      "p",
      "p",
      "p",
      "p",
      "p",
      "p",
      "p",
      "p",
      "ol",
      "ol",
      "ol",
      "ol",
      "ol",
      "ol",
      "ol",
      "ol",
      "ol",
      "li",
      "li",
      "li",
      "li",
      "li",
      "li",
      "p",
      "p",
      "p",
      "p",
      "p",
      "p",
      "strong",
      "li",
      "li",
      "li",
      "p",
      "p",
      "p",
      "strong",
      "ul",
      "li",
      "title"
    ],
    "why": [
      "h2"
    ],
    "a": [
      "p",
      "ol",
      "ol",
      "li",
      "li",
      "p",
      "p",
      "strong"
    ],
    "good": [
      "p"
    ],
    "validation": [
      "p",
      "p",
      "p",
      "ol",
      "li",
      "p",
      "ul",
      "li"
    ],
    "strategy": [
      "p",
      "ol",
      "li",
      "p"
    ],
    "is": [
      "p",
      "p",
      "p"
    ],
    "constrain": [
      "p",
      "p",
      "p",
      "ol",
      "ol",
      "li",
      "li",
      "p",
      "p",
      "strong"
    ],
    "known": [
      "p",
      "p"
    ],
    "valid": [
      "p",
      "ol",
      "ol",
      "ol",
      "li",
      "li",
      "li",
      "p",
      "p",
      "p",
      "strong"
    ],
    "values": [
      "p",
      "p",
      "p",
      "p"
    ],
    "reject": [
      "p"
    ],
    "bad": [
      "p",
      "p",
      "p",
      "p"
    ],
    "and": [
      "p"
    ],
    "sanitize": [
      "p"
    ],
    "the": [
      "p",
      "p",
      "p",
      "ol",
      "ol",
      "ol",
      "li",
      "p",
      "li",
      "li",
      "p",
      "p"
    ],
    "that": [
      "p",
      "ol",
      "ol",
      "li",
      "p",
      "li",
      "p",
      "ul",
      "li"
    ],
    "passes": [
      "p"
    ],
    "rejecting": [
      "p"
    ],
    "not": [
      "p",
      "ol",
      "li",
      "p"
    ],
    "be": [
      "p",
      "p",
      "ol",
      "li",
      "p",
      "ul",
      "li"
    ],
    "relied": [
      "p"
    ],
    "on": [
      "p"
    ],
    "because": [
      "p"
    ],
    "there": [
      "p"
    ],
    "are": [
      "p"
    ],
    "too": [
      "p"
    ],
    "many": [
      "p"
    ],
    "possible": [
      "p",
      "p"
    ],
    "however": [
      "p"
    ],
    "it": [
      "p"
    ],
    "filter": [
      "p"
    ],
    "out": [
      "p"
    ],
    "at": [
      "p"
    ],
    "least": [
      "p"
    ],
    "some": [
      "p",
      "ol",
      "li",
      "p"
    ],
    "constraining": [
      "p"
    ],
    "can": [
      "p",
      "ol",
      "li",
      "p",
      "ul",
      "li"
    ],
    "done": [
      "p"
    ],
    "effectively": [
      "p"
    ],
    "using": [
      "p",
      "p"
    ],
    "when": [
      "h2"
    ],
    "as": [
      "p",
      "ol",
      "ol",
      "ol",
      "li",
      "li",
      "p",
      "p",
      "li",
      "p"
    ],
    "first": [
      "p",
      "ol",
      "ol",
      "li",
      "p",
      "li",
      "p"
    ],
    "step": [
      "p",
      "ol",
      "li",
      "p"
    ],
    "of": [
      "p",
      "ol",
      "ol",
      "ol",
      "ol",
      "ol",
      "li",
      "li",
      "p",
      "p",
      "li",
      "li",
      "p",
      "p",
      "li",
      "p",
      "ul",
      "li"
    ],
    "how": [
      "h2"
    ],
    "perform": [
      "p"
    ],
    "following": [
      "p"
    ],
    "actions": [
      "p"
    ],
    "expression": [
      "ol",
      "ol",
      "ol",
      "li",
      "li",
      "li",
      "p",
      "p",
      "p",
      "strong"
    ],
    "library": [
      "ol",
      "ol",
      "li",
      "li",
      "p",
      "p",
      "strong"
    ],
    "c++": [
      "ol",
      "li",
      "p"
    ],
    "does": [
      "ol",
      "li",
      "p"
    ],
    "have": [
      "ol",
      "ol",
      "ol",
      "li",
      "p",
      "li",
      "p",
      "li",
      "p"
    ],
    "built": [
      "ol",
      "li",
      "p"
    ],
    "in": [
      "ol",
      "ol",
      "li",
      "p",
      "li",
      "p"
    ],
    "functionality": [
      "ol",
      "ol",
      "li",
      "li",
      "p",
      "p"
    ],
    "find": [
      "ol",
      "li",
      "p"
    ],
    "trusted": [
      "ol",
      "li",
      "p"
    ],
    "provides": [
      "ol",
      "li",
      "p"
    ],
    "determine": [
      "ol",
      "li",
      "p",
      "strong"
    ],
    "patterns": [
      "ol",
      "ol",
      "ol",
      "li",
      "li",
      "li",
      "p",
      "p",
      "p",
      "strong",
      "p"
    ],
    "identify": [
      "ol",
      "li",
      "p"
    ],
    "types": [
      "ol",
      "ol",
      "li",
      "li",
      "p",
      "p"
    ],
    "for": [
      "ol",
      "ol",
      "ol",
      "li",
      "li",
      "li",
      "p",
      "p",
      "p",
      "ul",
      "ul",
      "li",
      "li"
    ],
    "your": [
      "ol",
      "ol",
      "ol",
      "li",
      "li",
      "p",
      "p",
      "li",
      "p"
    ],
    "application": [
      "ol",
      "ol",
      "li",
      "li",
      "p",
      "p"
    ],
    "example": [
      "ol",
      "li",
      "p"
    ],
    "follows": [
      "ol",
      "li",
      "p"
    ],
    "obvious": [
      "ol",
      "ol",
      "li",
      "li",
      "p",
      "p"
    ],
    "such": [
      "ol",
      "ol",
      "li",
      "li",
      "p",
      "p"
    ],
    "social": [
      "ol",
      "li",
      "p"
    ],
    "security": [
      "ol",
      "li",
      "p"
    ],
    "or": [
      "ol",
      "li",
      "p"
    ],
    "credit": [
      "ol",
      "li",
      "p"
    ],
    "card": [
      "ol",
      "li",
      "p"
    ],
    "numbers": [
      "ol",
      "li",
      "p"
    ],
    "other": [
      "ol",
      "li",
      "p"
    ],
    "may": [
      "ol",
      "li",
      "p"
    ],
    "less": [
      "ol",
      "li",
      "p"
    ],
    "file": [
      "ol",
      "li",
      "p"
    ],
    "names": [
      "ol",
      "li",
      "p"
    ],
    "write": [
      "ol",
      "li",
      "p"
    ],
    "describe": [
      "ol",
      "li",
      "p"
    ],
    "length": [
      "ol",
      "ol",
      "li",
      "li",
      "p",
      "p",
      "strong"
    ],
    "before": [
      "ol",
      "li",
      "p",
      "strong"
    ],
    "applying": [
      "ol",
      "ol",
      "li",
      "li",
      "p",
      "p",
      "strong"
    ],
    "very": [
      "ol",
      "li",
      "p"
    ],
    "long": [
      "ol",
      "li",
      "p"
    ],
    "data": [
      "ol",
      "ol",
      "li",
      "li",
      "p",
      "p"
    ],
    "result": [
      "ol",
      "li",
      "p"
    ],
    "denial": [
      "ol",
      "li",
      "p"
    ],
    "service": [
      "ol",
      "li",
      "p"
    ],
    "conditions": [
      "ol",
      "li",
      "p"
    ],
    "so": [
      "ol",
      "li",
      "p"
    ],
    "should": [
      "ol",
      "li",
      "p"
    ],
    "validated": [
      "ol",
      "li",
      "p"
    ],
    "you": [
      "ol",
      "li",
      "p"
    ],
    "written": [
      "ol",
      "li",
      "p"
    ],
    "additional": [
      "h2"
    ],
    "resources": [
      "h2"
    ],
    "examples": [
      "ul",
      "li"
    ],
    "used": [
      "ul",
      "li"
    ],
    "see": [
      "ul",
      "li"
    ],
    "https//wwwowasporg/indexphp/owasp_validation_regex_repository": [
      "ul",
      "li",
      "a"
    ],
    "adapted": [
      "p"
    ],
    "from": [
      "p"
    ],
    "microsoft": [
      "p"
    ],
    "&": [
      "p"
    ],
    "practices": [
      "p"
    ],
    "guidance": [
      "p"
    ]
  },
  "tags": {},
  "links": [
    {
      "href": "https://www.owasp.org/index.php/OWASP_Validation_Regex_Repository",
      "text": "https://www.owasp.org/index.php/OWASP_Validation_Regex_Repository"
    }
  ]
}