{
  "id": "4de5ae59-81b7-4886-acda-a8e16f4ec66d",
  "checksum": "0e71258ae457ca3b79e394c80de1f1d3",
  "words": {
    "82": [
      "ul",
      "li",
      "title"
    ],
    "applies": [
      "h2"
    ],
    "to": [
      "h2"
    ],
    "pci": [
      "ul",
      "li"
    ],
    "dss": [
      "ul",
      "li"
    ],
    "requirement": [
      "ul",
      "li"
    ],
    "policy": [
      "h2",
      "h2"
    ],
    "statement": [
      "h2"
    ],
    "require": [
      "p",
      "ul",
      "li",
      "a",
      "title"
    ],
    "authentication": [
      "p",
      "p",
      "ul",
      "li",
      "a",
      "ul",
      "li",
      "a",
      "title"
    ],
    "for": [
      "p",
      "ul",
      "li",
      "a",
      "ul",
      "li",
      "a",
      "title"
    ],
    "all": [
      "p",
      "ul",
      "li",
      "a",
      "ul",
      "li",
      "a",
      "title"
    ],
    "users": [
      "p",
      "ul",
      "li",
      "a",
      "ul",
      "li",
      "a",
      "title"
    ],
    "purpose": [
      "h2"
    ],
    "controls": [
      "p"
    ],
    "help": [
      "p"
    ],
    "prevent": [
      "p"
    ],
    "unauthorized": [
      "p"
    ],
    "access": [
      "p"
    ],
    "related": [
      "h2",
      "h2"
    ],
    "guidance": [
      "h2"
    ],
    "checklist": [
      "h2"
    ],
    "items": [
      "h2"
    ],
    "is": [
      "ul",
      "li",
      "a"
    ],
    "required": [
      "ul",
      "li",
      "a"
    ]
  },
  "tags": {},
  "links": [
    {
      "href": "fa21c54f-e5a7-45a9-a80f-9eb9b147c1d6",
      "text": "Require Authentication for All Users"
    },
    {
      "href": "9046066b-b361-4af2-b3aa-b42a2220d77a",
      "text": "Authentication Is Required for All Users"
    }
  ]
}