{
  "id": "05caeab2-ecad-40a5-a71b-df7c9391222d",
  "checksum": "98fb7bb71a6ba0d4a4952cfd4d1435f0",
  "words": {
    "applies": [
      "h1"
    ],
    "to": [
      "h1",
      "h1",
      "p"
    ],
    "pci": [
      "ul",
      "li"
    ],
    "dss": [
      "ul",
      "li"
    ],
    "requirement": [
      "ul",
      "li"
    ],
    "11.5.a": [
      "ul",
      "li"
    ],
    "what": [
      "h1"
    ],
    "do": [
      "h1"
    ],
    "document": [
      "p",
      "p",
      "title"
    ],
    "all": [
      "p"
    ],
    "used": [
      "p",
      "p",
      "p",
      "p",
      "p",
      "title"
    ],
    "services": [
      "p",
      "p",
      "p",
      "p",
      "p"
    ],
    "protocols": [
      "p"
    ],
    "and": [
      "p",
      "p",
      "p",
      "p",
      "p"
    ],
    "ports": [
      "p",
      "title"
    ],
    "why": [
      "p",
      "h1",
      "p"
    ],
    "they": [
      "p"
    ],
    "are": [
      "p",
      "p",
      "p",
      "p"
    ],
    "necessary": [
      "p",
      "p",
      "p"
    ],
    "for": [
      "p",
      "p",
      "p",
      "p"
    ],
    "business": [
      "p",
      "p",
      "p"
    ],
    "documenting": [
      "p",
      "p"
    ],
    "the": [
      "p",
      "p",
      "p",
      "p",
      "p",
      "p",
      "p",
      "p",
      "p",
      "p",
      "p",
      "p",
      "p"
    ],
    "that": [
      "p",
      "p",
      "p",
      "p",
      "p",
      "p"
    ],
    "being": [
      "p",
      "p",
      "p"
    ],
    "is": [
      "p",
      "p",
      "p",
      "p"
    ],
    "important": [
      "p"
    ],
    "designing": [
      "p"
    ],
    "evaluating": [
      "p"
    ],
    "firewall": [
      "p",
      "p"
    ],
    "policy": [
      "p"
    ],
    "fewer": [
      "p"
    ],
    "smaller": [
      "p"
    ],
    "potential": [
      "p"
    ],
    "target": [
      "p"
    ],
    "surface": [
      "p"
    ],
    "presented": [
      "p"
    ],
    "attacker": [
      "p"
    ],
    "helps": [
      "p"
    ],
    "make": [
      "p",
      "p"
    ],
    "sure": [
      "p",
      "p"
    ],
    "there": [
      "p"
    ],
    "no": [
      "p"
    ],
    "running": [
      "p"
    ],
    "not": [
      "p"
    ],
    "needed": [
      "p"
    ],
    "how": [
      "h1"
    ],
    "identify": [
      "p",
      "p"
    ],
    "each": [
      "p",
      "p",
      "p"
    ],
    "service": [
      "p",
      "p",
      "p"
    ],
    "write": [
      "p"
    ],
    "a": [
      "p"
    ],
    "description": [
      "p",
      "p"
    ],
    "of": [
      "p",
      "p"
    ],
    "port": [
      "p",
      "p"
    ],
    "protocol": [
      "p",
      "p"
    ],
    "by": [
      "p"
    ],
    "together": [
      "p"
    ],
    "with": [
      "p"
    ],
    "network": [
      "p"
    ],
    "documentation": [
      "p"
    ],
    "matches": [
      "p"
    ],
    "configuration": [
      "p"
    ],
    "internet": [
      "p"
    ]
  },
  "tags": {},
  "links": []
}